mockquitto/__init__.py
mockquitto/broker.py
mockquitto/version.py
mockquitto/client/__init__.py
mockquitto/client/cli_utils.py
mockquitto/client/exceptions.py
mockquitto/client/mock_client.py
mockquitto/client/devices/__init__.py
mockquitto/client/devices/adc.py
mockquitto/client/devices/device.py
mockquitto/client/devices/factories.py
mockquitto/client/devices/gps.py
mockquitto/client/devices/humidity.py
mockquitto/client/devices/luminocity.py
mockquitto/client/devices/multipurpose.py
mockquitto/client/devices/temperature.py
mockquitto/client/devices/values.py
mockquitto/client/generator/__init__.py
mockquitto/client/generator/generator.py
mockquitto/client/generator/laws.py
mockquitto/scripts/__init__.py
mockquitto/scripts/broker.py
mockquitto/scripts/mqtt_generator.py
mockquitto/scripts/mqtt_generator_asyncio.py
mockquitto/utils/__init__.py
mockquitto/utils/helper_funcs.py
mockquitto/utils/prettify.py
mockquitto-0.0.4.dist-info/DESCRIPTION.rst
mockquitto-0.0.4.dist-info/METADATA
mockquitto-0.0.4.dist-info/RECORD
mockquitto-0.0.4.dist-info/WHEEL
mockquitto-0.0.4.dist-info/entry_points.txt
mockquitto-0.0.4.dist-info/metadata.json
mockquitto-0.0.4.dist-info/top_level.txt
scripts/__init__.py
scripts/broker.py
scripts/mqtt_generator.py
scripts/mqtt_generator_asyncio.py
